joyit_st7789vw-1.0.1.dist-info/licenses/LICENSE
st7789vw/__init__.py
st7789vw/st7789vw.py
joyit_st7789vw-1.0.1.dist-info/METADATA
joyit_st7789vw-1.0.1.dist-info/WHEEL
joyit_st7789vw-1.0.1.dist-info/top_level.txt
joyit_st7789vw-1.0.1.dist-info/RECORD
