Metadata-Version: 2.4
Name: JoyIT_st7789vw
Version: 1.0.1
Summary: Library to use the SBC-LCD01 with the Raspberry Pi
Home-page: https://github.com/joy-it/JoyIT_st7789vw
Author: Joy-IT
Author-email: Joy-IT <service@joy-it.net>
Project-URL: Homepage, https://github.com/joy-it/JoyIT_st7789vw
Project-URL: Issues, https://github.com/joy-it/JoyIT_st7789vw/issues
Classifier: Programming Language :: Python :: 3
Classifier: Operating System :: OS Independent
Requires-Python: >=3.7
License-File: LICENSE
Requires-Dist: gpiozero
Requires-Dist: spidev
Requires-Dist: numpy
Requires-Dist: Pillow
Dynamic: author
Dynamic: home-page
Dynamic: license-file
Dynamic: requires-python
